bitslicer9k.py
bitslicer9k-1.0.23.dist-info/METADATA
bitslicer9k-1.0.23.dist-info/WHEEL
bitslicer9k-1.0.23.dist-info/top_level.txt
bitslicer9k-1.0.23.dist-info/RECORD
