Metadata-Version: 2.1
Name: bitslicer9k
Version: 1.0.23
Summary: Super Fast Bit Slicer
Home-page: https://github.com/futzu/bitslicer9k
Author: fu-corp
Author-email: spam@futzu.com
License: UNKNOWN
Platform: all
Classifier: Programming Language :: Python :: 3
Classifier: License :: OSI Approved :: MIT License
Classifier: Operating System :: OS Independent
Requires-Python: >=3.1
